agentlabs/__init__.py
agentlabs/_internals/__init__.py
agentlabs/_internals/const.py
agentlabs/_internals/http.py
agentlabs/_internals/logger.py
agentlabs/_internals/realtime.py
agentlabs/_internals/utils.py
agentlabs/agent.py
agentlabs/attachment.py
agentlabs/chat.py
agentlabs/member.py
agentlabs/project.py
agentlabs_sdk-0.0.75.dist-info/METADATA
agentlabs_sdk-0.0.75.dist-info/WHEEL
agentlabs_sdk-0.0.75.dist-info/RECORD
