Metadata-Version: 2.1
Name: agentlabs-sdk
Version: 0.0.75
Summary: AgentLabs SDK for Python
Author: Aurélien Brabant
Author-email: aurel@agentlabs.dev
Requires-Python: >=3.9
Classifier: Programming Language :: Python :: 3
Classifier: Programming Language :: Python :: 3.9
Classifier: Programming Language :: Python :: 3.10
Classifier: Programming Language :: Python :: 3.11
Requires-Dist: python-socketio (>=5.9.0,<6.0.0)
Requires-Dist: requests (>=2.31.0,<3.0.0)
Requires-Dist: websocket-client (>=1.6.3,<2.0.0)
